<root>
  <message info="Receiver: 3838. From: 192.168.1.23:57699" type="Received">
    <packet>L2RlZXBsYWIvYm93bAAAACxpaQAAAABOAAAAkg==</packet>
  </message>
  <message info="Receiver: 3838. From: 192.168.1.23:57699" type="Received">
    <packet>L2RlZXBsYWIvYm93bAAAACxpaQAAAABNAAAAkg==</packet>
  </message>
  <message info="Receiver: 3838. From: 192.168.1.23:57699" type="Received">
    <packet>L2RlZXBsYWIvYm93bAAAACxpaQAAAABNAAAAkg==</packet>
  </message>
  <message info="Receiver: 3838. From: 192.168.1.23:57699" type="Received">
    <packet>L2RlZXBsYWIvYm93bAAAACxpaQAAAABOAAAAkQ==</packet>
  </message>
  <message info="Receiver: 3838. From: 192.168.1.23:57699" type="Received">
    <packet>L2RlZXBsYWIvYm93bAAAACxpaQAAAABOAAAAkg==</packet>
  </message>
  <message info="Receiver: 3838. From: 192.168.1.23:57699" type="Received">
    <packet>L2RlZXBsYWIvYm93bAAAACxpaQAAAABOAAAAkQ==</packet>
  </message>
  <message info="Receiver: 3838. From: 192.168.1.23:57699" type="Received">
    <packet>L2RlZXBsYWIvYm93bAAAACxpaQAAAABPAAAAkQ==</packet>
  </message>
  <message info="Receiver: 3838. From: 192.168.1.23:57699" type="Received">
    <packet>L2RlZXBsYWIvYm93bAAAACxpaQAAAABPAAAAkQ==</packet>
  </message>
  <message info="Receiver: 3838. From: 192.168.1.23:57699" type="Received">
    <packet>L2RlZXBsYWIvYm93bAAAACxpaQAAAABPAAAAkQ==</packet>
  </message>
  <message info="Receiver: 3838. From: 192.168.1.23:57699" type="Received">
    <packet>L2RlZXBsYWIvYm93bAAAACxpaQAAAABOAAAAkQ==</packet>
  </message>
  <message info="Receiver: 3838. From: 192.168.1.23:57699" type="Received">
    <packet>L2RlZXBsYWIvYm93bAAAACxpaQAAAABPAAAAkg==</packet>
  </message>
  <message info="Receiver: 3838. From: 192.168.1.23:57699" type="Received">
    <packet>L2RlZXBsYWIvYm93bAAAACxpaQAAAABOAAAAkg==</packet>
  </message>
  <message info="Receiver: 3838. From: 192.168.1.23:57699" type="Received">
    <packet>L2RlZXBsYWIvYm93bAAAACxpaQAAAABOAAAAkg==</packet>
  </message>
  <message info="Receiver: 3838. From: 192.168.1.23:57699" type="Received">
    <packet>L2RlZXBsYWIvYm93bAAAACxpaQAAAABPAAAAkQ==</packet>
  </message>
  <message info="Receiver: 3838. From: 192.168.1.23:57699" type="Received">
    <packet>L2RlZXBsYWIvYm93bAAAACxpaQAAAABOAAAAkg==</packet>
  </message>
  <message info="Receiver: 3838. From: 192.168.1.23:57699" type="Received">
    <packet>L2RlZXBsYWIvYm93bAAAACxpaQAAAABPAAAAkg==</packet>
  </message>
  <message info="Receiver: 3838. From: 192.168.1.23:57699" type="Received">
    <packet>L2RlZXBsYWIvYm93bAAAACxpaQAAAABOAAAAkg==</packet>
  </message>
  <message info="Receiver: 3838. From: 192.168.1.23:57699" type="Received">
    <packet>L2RlZXBsYWIvYm93bAAAACxpaQAAAABOAAAAkg==</packet>
  </message>
  <message info="Receiver: 3838. From: 192.168.1.23:57699" type="Received">
    <packet>L2RlZXBsYWIvYm93bAAAACxpaQAAAABOAAAAkw==</packet>
  </message>
  <message info="Receiver: 3838. From: 192.168.1.23:57699" type="Received">
    <packet>L2RlZXBsYWIvYm93bAAAACxpaQAAAABNAAAAkg==</packet>
  </message>
  <message info="Receiver: 3838. From: 192.168.1.23:57699" type="Received">
    <packet>L2RlZXBsYWIvYm93bAAAACxpaQAAAACWAAAAjg==</packet>
  </message>
  <message info="Receiver: 3838. From: 192.168.1.23:57699" type="Received">
    <packet>L2RlZXBsYWIvYm93bAAAACxpaQAAAABOAAAAkg==</packet>
  </message>
  <message info="Receiver: 3838. From: 192.168.1.23:57699" type="Received">
    <packet>L2RlZXBsYWIvYm93bAAAACxpaQAAAACZAAAAiw==</packet>
  </message>
  <message info="Receiver: 3838. From: 192.168.1.23:57699" type="Received">
    <packet>L2RlZXBsYWIvYm93bAAAACxpaQAAAABOAAAAkw==</packet>
  </message>
  <message info="Receiver: 3838. From: 192.168.1.23:57699" type="Received">
    <packet>L2RlZXBsYWIvYm93bAAAACxpaQAAAABOAAAAkw==</packet>
  </message>
  <message info="Receiver: 3838. From: 192.168.1.23:57699" type="Received">
    <packet>L2RlZXBsYWIvYm93bAAAACxpaQAAAABOAAAAkg==</packet>
  </message>
  <message info="Receiver: 3838. From: 192.168.1.23:57699" type="Received">
    <packet>L2RlZXBsYWIvYm93bAAAACxpaQAAAACYAAAAig==</packet>
  </message>
  <message info="Receiver: 3838. From: 192.168.1.23:57699" type="Received">
    <packet>L2RlZXBsYWIvYm93bAAAACxpaQAAAACXAAAAjQ==</packet>
  </message>
  <message info="Receiver: 3838. From: 192.168.1.23:57699" type="Received">
    <packet>L2RlZXBsYWIvYm93bAAAACxpaQAAAACYAAAAiw==</packet>
  </message>
  <message info="Receiver: 3838. From: 192.168.1.23:57699" type="Received">
    <packet>L2RlZXBsYWIvYm93bAAAACxpaQAAAABOAAAAkw==</packet>
  </message>
  <message info="Receiver: 3838. From: 192.168.1.23:57699" type="Received">
    <packet>L2RlZXBsYWIvYm93bAAAACxpaQAAAABOAAAAkg==</packet>
  </message>
  <message info="Receiver: 3838. From: 192.168.1.23:57699" type="Received">
    <packet>L2RlZXBsYWIvYm93bAAAACxpaQAAAABPAAAAkw==</packet>
  </message>
  <message info="Receiver: 3838. From: 192.168.1.23:57699" type="Received">
    <packet>L2RlZXBsYWIvYm93bAAAACxpaQAAAACXAAAAjA==</packet>
  </message>
  <message info="Receiver: 3838. From: 192.168.1.23:57699" type="Received">
    <packet>L2RlZXBsYWIvYm93bAAAACxpaQAAAABNAAAAkg==</packet>
  </message>
  <message info="Receiver: 3838. From: 192.168.1.23:57699" type="Received">
    <packet>L2RlZXBsYWIvYm93bAAAACxpaQAAAACYAAAAjA==</packet>
  </message>
  <message info="Receiver: 3838. From: 192.168.1.23:57699" type="Received">
    <packet>L2RlZXBsYWIvYm93bAAAACxpaQAAAABPAAAAkw==</packet>
  </message>
  <message info="Receiver: 3838. From: 192.168.1.23:57699" type="Received">
    <packet>L2RlZXBsYWIvYm93bAAAACxpaQAAAABOAAAAkw==</packet>
  </message>
  <message info="Receiver: 3838. From: 192.168.1.23:57699" type="Received">
    <packet>L2RlZXBsYWIvYm93bAAAACxpaQAAAABOAAAAkw==</packet>
  </message>
  <message info="Receiver: 3838. From: 192.168.1.23:57699" type="Received">
    <packet>L2RlZXBsYWIvYm93bAAAACxpaQAAAACYAAAAjQ==</packet>
  </message>
  <message info="Receiver: 3838. From: 192.168.1.23:57699" type="Received">
    <packet>L2RlZXBsYWIvYm93bAAAACxpaQAAAABOAAAAkw==</packet>
  </message>
  <message info="Receiver: 3838. From: 192.168.1.23:57699" type="Received">
    <packet>L2RlZXBsYWIvYm93bAAAACxpaQAAAABOAAAAkg==</packet>
  </message>
  <message info="Receiver: 3838. From: 192.168.1.23:57699" type="Received">
    <packet>L2RlZXBsYWIvYm93bAAAACxpaQAAAABOAAAAkw==</packet>
  </message>
  <message info="Receiver: 3838. From: 192.168.1.23:57699" type="Received">
    <packet>L2RlZXBsYWIvYm93bAAAACxpaQAAAACXAAAAiw==</packet>
  </message>
  <message info="Receiver: 3838. From: 192.168.1.23:57699" type="Received">
    <packet>L2RlZXBsYWIvYm93bAAAACxpaQAAAACXAAAAiw==</packet>
  </message>
  <message info="Receiver: 3838. From: 192.168.1.23:57699" type="Received">
    <packet>L2RlZXBsYWIvYm93bAAAACxpaQAAAABPAAAAkg==</packet>
  </message>
  <message info="Receiver: 3838. From: 192.168.1.23:57699" type="Received">
    <packet>L2RlZXBsYWIvYm93bAAAACxpaQAAAABMAAAAkw==</packet>
  </message>
  <message info="Receiver: 3838. From: 192.168.1.23:57699" type="Received">
    <packet>L2RlZXBsYWIvYm93bAAAACxpaQAAAABMAAAAkg==</packet>
  </message>
  <message info="Receiver: 3838. From: 192.168.1.23:57699" type="Received">
    <packet>L2RlZXBsYWIvYm93bAAAACxpaQAAAACZAAAAiw==</packet>
  </message>
  <message info="Receiver: 3838. From: 192.168.1.23:57699" type="Received">
    <packet>L2RlZXBsYWIvYm93bAAAACxpaQAAAACYAAAAjQ==</packet>
  </message>
  <message info="Receiver: 3838. From: 192.168.1.23:57699" type="Received">
    <packet>L2RlZXBsYWIvYm93bAAAACxpaQAAAABMAAAAkg==</packet>
  </message>
  <message info="Receiver: 3838. From: 192.168.1.23:57699" type="Received">
    <packet>L2RlZXBsYWIvYm93bAAAACxpaQAAAABQAAAAlA==</packet>
  </message>
  <message info="Receiver: 3838. From: 192.168.1.23:57699" type="Received">
    <packet>L2RlZXBsYWIvYm93bAAAACxpaQAAAABMAAAAlA==</packet>
  </message>
  <message info="Receiver: 3838. From: 192.168.1.23:57699" type="Received">
    <packet>L2RlZXBsYWIvYm93bAAAACxpaQAAAABLAAAAlA==</packet>
  </message>
  <message info="Receiver: 3838. From: 192.168.1.23:57699" type="Received">
    <packet>L2RlZXBsYWIvYm93bAAAACxpaQAAAABKAAAAlg==</packet>
  </message>
  <message info="Receiver: 3838. From: 192.168.1.23:57699" type="Received">
    <packet>L2RlZXBsYWIvYm93bAAAACxpaQAAAABLAAAAlQ==</packet>
  </message>
  <message info="Receiver: 3838. From: 192.168.1.23:57699" type="Received">
    <packet>L2RlZXBsYWIvYm93bAAAACxpaQAAAABKAAAAlQ==</packet>
  </message>
  <message info="Receiver: 3838. From: 192.168.1.23:57699" type="Received">
    <packet>L2RlZXBsYWIvYm93bAAAACxpaQAAAABLAAAAlg==</packet>
  </message>
  <message info="Receiver: 3838. From: 192.168.1.23:57699" type="Received">
    <packet>L2RlZXBsYWIvYm93bAAAACxpaQAAAABSAAAAlw==</packet>
  </message>
  <message info="Receiver: 3838. From: 192.168.1.23:57699" type="Received">
    <packet>L2RlZXBsYWIvYm93bAAAACxpaQAAAACYAAAAjw==</packet>
  </message>
  <message info="Receiver: 3838. From: 192.168.1.23:57699" type="Received">
    <packet>L2RlZXBsYWIvYm93bAAAACxpaQAAAACYAAAAjw==</packet>
  </message>
  <message info="Receiver: 3838. From: 192.168.1.23:57699" type="Received">
    <packet>L2RlZXBsYWIvYm93bAAAACxpaQAAAABMAAAAlw==</packet>
  </message>
  <message info="Receiver: 3838. From: 192.168.1.23:57699" type="Received">
    <packet>L2RlZXBsYWIvYm93bAAAACxpaQAAAABSAAAAlA==</packet>
  </message>
  <message info="Receiver: 3838. From: 192.168.1.23:57699" type="Received">
    <packet>L2RlZXBsYWIvYm93bAAAACxpaQAAAABSAAAAlw==</packet>
  </message>
  <message info="Receiver: 3838. From: 192.168.1.23:57699" type="Received">
    <packet>L2RlZXBsYWIvYm93bAAAACxpaQAAAAB/AAAAig==</packet>
  </message>
  <message info="Receiver: 3838. From: 192.168.1.23:57699" type="Received">
    <packet>L2RlZXBsYWIvYm93bAAAACxpaQAAAACuAAAAkg==</packet>
  </message>
  <message info="Receiver: 3838. From: 192.168.1.23:57699" type="Received">
    <packet>L2RlZXBsYWIvYm93bAAAACxpaQAAAACVAAAAkg==</packet>
  </message>
  <message info="Receiver: 3838. From: 192.168.1.23:57699" type="Received">
    <packet>L2RlZXBsYWIvYm93bAAAACxpaQAAAACZAAAAkg==</packet>
  </message>
  <message info="Receiver: 3838. From: 192.168.1.23:57699" type="Received">
    <packet>L2RlZXBsYWIvYm93bAAAACxpaQAAAACrAAAAkw==</packet>
  </message>
  <message info="Receiver: 3838. From: 192.168.1.23:57699" type="Received">
    <packet>L2RlZXBsYWIvYm93bAAAACxpaQAAAACrAAAAkw==</packet>
  </message>
  <message info="Receiver: 3838. From: 192.168.1.23:57699" type="Received">
    <packet>L2RlZXBsYWIvYm93bAAAACxpaQAAAACrAAAAkw==</packet>
  </message>
  <message info="Receiver: 3838. From: 192.168.1.23:57699" type="Received">
    <packet>L2RlZXBsYWIvYm93bAAAACxpaQAAAACqAAAAkw==</packet>
  </message>
  <message info="Receiver: 3838. From: 192.168.1.23:57699" type="Received">
    <packet>L2RlZXBsYWIvYm93bAAAACxpaQAAAACrAAAAkg==</packet>
  </message>
  <message info="Receiver: 3838. From: 192.168.1.23:57699" type="Received">
    <packet>L2RlZXBsYWIvYm93bAAAACxpaQAAAACaAAAAkw==</packet>
  </message>
  <message info="Receiver: 3838. From: 192.168.1.23:57699" type="Received">
    <packet>L2RlZXBsYWIvYm93bAAAACxpaQAAAAFWAAAAkg==</packet>
  </message>
  <message info="Receiver: 3838. From: 192.168.1.23:57699" type="Received">
    <packet>L2RlZXBsYWIvYm93bAAAACxpaQAAAAFWAAAAkw==</packet>
  </message>
  <message info="Receiver: 3838. From: 192.168.1.23:57699" type="Received">
    <packet>L2RlZXBsYWIvYm93bAAAACxpaQAAAAFWAAAAkg==</packet>
  </message>
  <message info="Receiver: 3838. From: 192.168.1.23:57699" type="Received">
    <packet>L2RlZXBsYWIvYm93bAAAACxpaQAAAAFWAAAAkg==</packet>
  </message>
  <message info="Receiver: 3838. From: 192.168.1.23:57699" type="Received">
    <packet>L2RlZXBsYWIvYm93bAAAACxpaQAAAAGMAAAAnQ==</packet>
  </message>
  <message info="Receiver: 3838. From: 192.168.1.23:57699" type="Received">
    <packet>L2RlZXBsYWIvYm93bAAAACxpaQAAAAGcAAAAmQ==</packet>
  </message>
  <message info="Receiver: 3838. From: 192.168.1.23:57699" type="Received">
    <packet>L2RlZXBsYWIvYm93bAAAACxpaQAAAAGcAAAAmQ==</packet>
  </message>
  <message info="Receiver: 3838. From: 192.168.1.23:57699" type="Received">
    <packet>L2RlZXBsYWIvYm93bAAAACxpaQAAAAGcAAAAmQ==</packet>
  </message>
  <message info="Receiver: 3838. From: 192.168.1.23:57699" type="Received">
    <packet>L2RlZXBsYWIvYm93bAAAACxpaQAAAAGcAAAAmA==</packet>
  </message>
  <message info="Receiver: 3838. From: 192.168.1.23:57699" type="Received">
    <packet>L2RlZXBsYWIvYm93bAAAACxpaQAAAAGcAAAAmQ==</packet>
  </message>
  <message info="Receiver: 3838. From: 192.168.1.23:57699" type="Received">
    <packet>L2RlZXBsYWIvYm93bAAAACxpaQAAAAGcAAAAmQ==</packet>
  </message>
  <message info="Receiver: 3838. From: 192.168.1.23:57699" type="Received">
    <packet>L2RlZXBsYWIvYm93bAAAACxpaQAAAAGcAAAAmQ==</packet>
  </message>
  <message info="Receiver: 3838. From: 192.168.1.23:57699" type="Received">
    <packet>L2RlZXBsYWIvYm93bAAAACxpaQAAAAFNAAAAow==</packet>
  </message>
  <message info="Receiver: 3838. From: 192.168.1.23:57699" type="Received">
    <packet>L2RlZXBsYWIvYm93bAAAACxpaQAAAAFUAAAApA==</packet>
  </message>
  <message info="Receiver: 3838. From: 192.168.1.23:57699" type="Received">
    <packet>L2RlZXBsYWIvYm93bAAAACxpaQAAAAFVAAAApA==</packet>
  </message>
  <message info="Receiver: 3838. From: 192.168.1.23:57699" type="Received">
    <packet>L2RlZXBsYWIvYm93bAAAACxpaQAAAAFUAAAApA==</packet>
  </message>
  <message info="Receiver: 3838. From: 192.168.1.23:57699" type="Received">
    <packet>L2RlZXBsYWIvYm93bAAAACxpaQAAAAFWAAAApA==</packet>
  </message>
  <message info="Receiver: 3838. From: 192.168.1.23:57699" type="Received">
    <packet>L2RlZXBsYWIvYm93bAAAACxpaQAAAAFSAAAApA==</packet>
  </message>
  <message info="Receiver: 3838. From: 192.168.1.23:57699" type="Received">
    <packet>L2RlZXBsYWIvYm93bAAAACxpaQAAAAFSAAAApA==</packet>
  </message>
  <message info="Receiver: 3838. From: 192.168.1.23:57699" type="Received">
    <packet>L2RlZXBsYWIvYm93bAAAACxpaQAAAAFTAAAApQ==</packet>
  </message>
  <message info="Receiver: 3838. From: 192.168.1.23:57699" type="Received">
    <packet>L2RlZXBsYWIvYm93bAAAACxpaQAAAAFSAAAAog==</packet>
  </message>
  <message info="Receiver: 3838. From: 192.168.1.23:57699" type="Received">
    <packet>L2RlZXBsYWIvYm93bAAAACxpaQAAAACiAAAAkw==</packet>
  </message>
  <message info="Receiver: 3838. From: 192.168.1.23:57699" type="Received">
    <packet>L2RlZXBsYWIvYm93bAAAACxpaQAAAACiAAAAkw==</packet>
  </message>
  <message info="Receiver: 3838. From: 192.168.1.23:57699" type="Received">
    <packet>L2RlZXBsYWIvYm93bAAAACxpaQAAAACiAAAAlA==</packet>
  </message>
  <message info="Receiver: 3838. From: 192.168.1.23:57699" type="Received">
    <packet>L2RlZXBsYWIvYm93bAAAACxpaQAAAAC4AAAAlA==</packet>
  </message>
  <message info="Receiver: 3838. From: 192.168.1.23:57699" type="Received">
    <packet>L2RlZXBsYWIvYm93bAAAACxpaQAAAACiAAAAkw==</packet>
  </message>
  <message info="Receiver: 3838. From: 192.168.1.23:57699" type="Received">
    <packet>L2RlZXBsYWIvYm93bAAAACxpaQAAAACiAAAAlA==</packet>
  </message>
  <message info="Receiver: 3838. From: 192.168.1.23:57699" type="Received">
    <packet>L2RlZXBsYWIvYm93bAAAACxpaQAAAAC4AAAAkw==</packet>
  </message>
  <message info="Receiver: 3838. From: 192.168.1.23:57699" type="Received">
    <packet>L2RlZXBsYWIvYm93bAAAACxpaQAAAAC4AAAAlQ==</packet>
  </message>
  <message info="Receiver: 3838. From: 192.168.1.23:57699" type="Received">
    <packet>L2RlZXBsYWIvYm93bAAAACxpaQAAAACiAAAAkw==</packet>
  </message>
  <message info="Receiver: 3838. From: 192.168.1.23:57699" type="Received">
    <packet>L2RlZXBsYWIvYm93bAAAACxpaQAAAAC4AAAAkw==</packet>
  </message>
  <message info="Receiver: 3838. From: 192.168.1.23:57699" type="Received">
    <packet>L2RlZXBsYWIvYm93bAAAACxpaQAAAACiAAAAkw==</packet>
  </message>
  <message info="Receiver: 3838. From: 192.168.1.23:57699" type="Received">
    <packet>L2RlZXBsYWIvYm93bAAAACxpaQAAAAClAAAAlQ==</packet>
  </message>
  <message info="Receiver: 3838. From: 192.168.1.23:57699" type="Received">
    <packet>L2RlZXBsYWIvYm93bAAAACxpaQAAAAC3AAAAkw==</packet>
  </message>
  <message info="Receiver: 3838. From: 192.168.1.23:57699" type="Received">
    <packet>L2RlZXBsYWIvYm93bAAAACxpaQAAAAC5AAAAlA==</packet>
  </message>
  <message info="Receiver: 3838. From: 192.168.1.23:57699" type="Received">
    <packet>L2RlZXBsYWIvYm93bAAAACxpaQAAAACiAAAAlA==</packet>
  </message>
  <message info="Receiver: 3838. From: 192.168.1.23:57699" type="Received">
    <packet>L2RlZXBsYWIvYm93bAAAACxpaQAAAACjAAAAkw==</packet>
  </message>
  <message info="Receiver: 3838. From: 192.168.1.23:57699" type="Received">
    <packet>L2RlZXBsYWIvYm93bAAAACxpaQAAAAGXAAAArA==</packet>
  </message>
  <message info="Receiver: 3838. From: 192.168.1.23:57699" type="Received">
    <packet>L2RlZXBsYWIvYm93bAAAACxpaQAAAAGYAAAArQ==</packet>
  </message>
  <message info="Receiver: 3838. From: 192.168.1.23:57699" type="Received">
    <packet>L2RlZXBsYWIvYm93bAAAACxpaQAAAAGXAAAArA==</packet>
  </message>
  <message info="Receiver: 3838. From: 192.168.1.23:57699" type="Received">
    <packet>L2RlZXBsYWIvYm93bAAAACxpaQAAAAGXAAAArA==</packet>
  </message>
  <message info="Receiver: 3838. From: 192.168.1.23:57699" type="Received">
    <packet>L2RlZXBsYWIvYm93bAAAACxpaQAAAAGXAAAArQ==</packet>
  </message>
  <message info="Receiver: 3838. From: 192.168.1.23:57699" type="Received">
    <packet>L2RlZXBsYWIvYm93bAAAACxpaQAAAAGXAAAArQ==</packet>
  </message>
  <message info="Receiver: 3838. From: 192.168.1.23:57699" type="Received">
    <packet>L2RlZXBsYWIvYm93bAAAACxpaQAAAAGXAAAArQ==</packet>
  </message>
  <message info="Receiver: 3838. From: 192.168.1.23:57699" type="Received">
    <packet>L2RlZXBsYWIvYm93bAAAACxpaQAAAAFJAAAApQ==</packet>
  </message>
  <message info="Receiver: 3838. From: 192.168.1.23:57699" type="Received">
    <packet>L2RlZXBsYWIvYm93bAAAACxpaQAAAAE7AAAAnA==</packet>
  </message>
  <message info="Receiver: 3838. From: 192.168.1.23:57699" type="Received">
    <packet>L2RlZXBsYWIvYm93bAAAACxpaQAAAAE8AAAAnA==</packet>
  </message>
  <message info="Receiver: 3838. From: 192.168.1.23:57699" type="Received">
    <packet>L2RlZXBsYWIvYm93bAAAACxpaQAAAAE7AAAAnQ==</packet>
  </message>
  <message info="Receiver: 3838. From: 192.168.1.23:57699" type="Received">
    <packet>L2RlZXBsYWIvYm93bAAAACxpaQAAAAE7AAAAnA==</packet>
  </message>
  <message info="Receiver: 3838. From: 192.168.1.23:57699" type="Received">
    <packet>L2RlZXBsYWIvYm93bAAAACxpaQAAAAE7AAAAnQ==</packet>
  </message>
  <message info="Receiver: 3838. From: 192.168.1.23:57699" type="Received">
    <packet>L2RlZXBsYWIvYm93bAAAACxpaQAAAAE7AAAAnQ==</packet>
  </message>
  <message info="Receiver: 3838. From: 192.168.1.23:57699" type="Received">
    <packet>L2RlZXBsYWIvYm93bAAAACxpaQAAAAE7AAAAnA==</packet>
  </message>
  <message info="Receiver: 3838. From: 192.168.1.23:57699" type="Received">
    <packet>L2RlZXBsYWIvYm93bAAAACxpaQAAAAE8AAAAnA==</packet>
  </message>
  <message info="Receiver: 3838. From: 192.168.1.23:57699" type="Received">
    <packet>L2RlZXBsYWIvYm93bAAAACxpaQAAAAE8AAAAnA==</packet>
  </message>
  <message info="Receiver: 3838. From: 192.168.1.23:57699" type="Received">
    <packet>L2RlZXBsYWIvYm93bAAAACxpaQAAAAE7AAAAnQ==</packet>
  </message>
  <message info="Receiver: 3838. From: 192.168.1.23:57699" type="Received">
    <packet>L2RlZXBsYWIvYm93bAAAACxpaQAAAAE7AAAAnA==</packet>
  </message>
  <message info="Receiver: 3838. From: 192.168.1.23:57699" type="Received">
    <packet>L2RlZXBsYWIvYm93bAAAACxpaQAAAAE7AAAAnA==</packet>
  </message>
  <message info="Receiver: 3838. From: 192.168.1.23:57699" type="Received">
    <packet>L2RlZXBsYWIvYm93bAAAACxpaQAAAAE8AAAAnQ==</packet>
  </message>
  <message info="Receiver: 3838. From: 192.168.1.23:57699" type="Received">
    <packet>L2RlZXBsYWIvYm93bAAAACxpaQAAAAE7AAAAnQ==</packet>
  </message>
  <message info="Receiver: 3838. From: 192.168.1.23:57699" type="Received">
    <packet>L2RlZXBsYWIvYm93bAAAACxpaQAAAAE7AAAAnA==</packet>
  </message>
  <message info="Receiver: 3838. From: 192.168.1.23:57699" type="Received">
    <packet>L2RlZXBsYWIvYm93bAAAACxpaQAAAAE7AAAAnA==</packet>
  </message>
  <message info="Receiver: 3838. From: 192.168.1.23:57699" type="Received">
    <packet>L2RlZXBsYWIvYm93bAAAACxpaQAAAAE8AAAAmw==</packet>
  </message>
  <message info="Receiver: 3838. From: 192.168.1.23:48547" type="Received">
    <packet>L2RlZXBsYWIvYm93bAAAACxpaQAAAACcAAABPA==</packet>
  </message>
  <message info="Receiver: 3838. From: 192.168.1.23:48547" type="Received">
    <packet>L2RlZXBsYWIvYm93bAAAACxpaQAAAACcAAABPA==</packet>
  </message>
  <message info="Receiver: 3838. From: 192.168.1.23:48547" type="Received">
    <packet>L2RlZXBsYWIvYm93bAAAACxpaQAAAACcAAABPA==</packet>
  </message>
  <message info="Receiver: 3838. From: 192.168.1.23:48547" type="Received">
    <packet>L2RlZXBsYWIvYm93bAAAACxpaQAAAACdAAABPA==</packet>
  </message>
  <message info="Receiver: 3838. From: 192.168.1.23:48547" type="Received">
    <packet>L2RlZXBsYWIvYm93bAAAACxpaQAAAACdAAABPA==</packet>
  </message>
  <message info="Receiver: 3838. From: 192.168.1.23:48547" type="Received">
    <packet>L2RlZXBsYWIvYm93bAAAACxpaQAAAACcAAABPA==</packet>
  </message>
  <message info="Receiver: 3838. From: 192.168.1.23:48547" type="Received">
    <packet>L2RlZXBsYWIvYm93bAAAACxpaQAAAACcAAABPA==</packet>
  </message>
  <message info="Receiver: 3838. From: 192.168.1.23:48547" type="Received">
    <packet>L2RlZXBsYWIvYm93bAAAACxpaQAAAACcAAABPA==</packet>
  </message>
  <message info="Receiver: 3838. From: 192.168.1.23:48547" type="Received">
    <packet>L2RlZXBsYWIvYm93bAAAACxpaQAAAACdAAABPA==</packet>
  </message>
  <message info="Receiver: 3838. From: 192.168.1.23:48547" type="Received">
    <packet>L2RlZXBsYWIvYm93bAAAACxpaQAAAACcAAABPA==</packet>
  </message>
  <message info="Receiver: 3838. From: 192.168.1.23:48547" type="Received">
    <packet>L2RlZXBsYWIvYm93bAAAACxpaQAAAACcAAABPA==</packet>
  </message>
  <message info="Receiver: 3838. From: 192.168.1.23:48547" type="Received">
    <packet>L2RlZXBsYWIvYm93bAAAACxpaQAAAACcAAABPA==</packet>
  </message>
  <message info="Receiver: 3838. From: 192.168.1.23:48547" type="Received">
    <packet>L2RlZXBsYWIvYm93bAAAACxpaQAAAACcAAABPA==</packet>
  </message>
  <message info="Receiver: 3838. From: 192.168.1.23:48547" type="Received">
    <packet>L2RlZXBsYWIvYm93bAAAACxpaQAAAACcAAABPA==</packet>
  </message>
  <message info="Receiver: 3838. From: 192.168.1.23:48547" type="Received">
    <packet>L2RlZXBsYWIvYm93bAAAACxpaQAAAACdAAABOw==</packet>
  </message>
  <message info="Receiver: 3838. From: 192.168.1.23:48547" type="Received">
    <packet>L2RlZXBsYWIvYm93bAAAACxpaQAAAACcAAABPA==</packet>
  </message>
  <message info="Receiver: 3838. From: 192.168.1.23:48547" type="Received">
    <packet>L2RlZXBsYWIvYm93bAAAACxpaQAAAACcAAABPA==</packet>
  </message>
  <message info="Receiver: 3838. From: 192.168.1.23:48547" type="Received">
    <packet>L2RlZXBsYWIvYm93bAAAACxpaQAAAACcAAABPA==</packet>
  </message>
  <message info="Receiver: 3838. From: 192.168.1.23:48547" type="Received">
    <packet>L2RlZXBsYWIvYm93bAAAACxpaQAAAACcAAABPA==</packet>
  </message>
  <message info="Receiver: 3838. From: 192.168.1.23:48547" type="Received">
    <packet>L2RlZXBsYWIvYm93bAAAACxpaQAAAACcAAABPA==</packet>
  </message>
  <message info="Receiver: 3838. From: 192.168.1.23:48547" type="Received">
    <packet>L2RlZXBsYWIvYm93bAAAACxpaQAAAACcAAABOw==</packet>
  </message>
  <message info="Receiver: 3838. From: 192.168.1.23:48547" type="Received">
    <packet>L2RlZXBsYWIvYm93bAAAACxpaQAAAACcAAABPA==</packet>
  </message>
  <message info="Receiver: 3838. From: 192.168.1.23:48547" type="Received">
    <packet>L2RlZXBsYWIvYm93bAAAACxpaQAAAACcAAABPA==</packet>
  </message>
  <message info="Receiver: 3838. From: 192.168.1.23:48547" type="Received">
    <packet>L2RlZXBsYWIvYm93bAAAACxpaQAAAACcAAABPA==</packet>
  </message>
  <message info="Receiver: 3838. From: 192.168.1.23:48547" type="Received">
    <packet>L2RlZXBsYWIvYm93bAAAACxpaQAAAACcAAABPA==</packet>
  </message>
  <message info="Receiver: 3838. From: 192.168.1.23:48547" type="Received">
    <packet>L2RlZXBsYWIvYm93bAAAACxpaQAAAACdAAABPA==</packet>
  </message>
  <message info="Receiver: 3838. From: 192.168.1.23:48547" type="Received">
    <packet>L2RlZXBsYWIvYm93bAAAACxpaQAAAACcAAAA5g==</packet>
  </message>
  <message info="Receiver: 3838. From: 192.168.1.23:48547" type="Received">
    <packet>L2RlZXBsYWIvYm93bAAAACxpaQAAAACdAAABPA==</packet>
  </message>
  <message info="Receiver: 3838. From: 192.168.1.23:48547" type="Received">
    <packet>L2RlZXBsYWIvYm93bAAAACxpaQAAAACcAAABPA==</packet>
  </message>
  <message info="Receiver: 3838. From: 192.168.1.23:48547" type="Received">
    <packet>L2RlZXBsYWIvYm93bAAAACxpaQAAAACcAAABPA==</packet>
  </message>
  <message info="Receiver: 3838. From: 192.168.1.23:48547" type="Received">
    <packet>L2RlZXBsYWIvYm93bAAAACxpaQAAAACcAAABOw==</packet>
  </message>
  <message info="Receiver: 3838. From: 192.168.1.23:48547" type="Received">
    <packet>L2RlZXBsYWIvYm93bAAAACxpaQAAAACcAAABPQ==</packet>
  </message>
  <message info="Receiver: 3838. From: 192.168.1.23:48547" type="Received">
    <packet>L2RlZXBsYWIvYm93bAAAACxpaQAAAACcAAABOw==</packet>
  </message>
  <message info="Receiver: 3838. From: 192.168.1.23:48547" type="Received">
    <packet>L2RlZXBsYWIvYm93bAAAACxpaQAAAACcAAABPA==</packet>
  </message>
  <message info="Receiver: 3838. From: 192.168.1.23:48547" type="Received">
    <packet>L2RlZXBsYWIvYm93bAAAACxpaQAAAACcAAABPQ==</packet>
  </message>
  <message info="Receiver: 3838. From: 192.168.1.23:48547" type="Received">
    <packet>L2RlZXBsYWIvYm93bAAAACxpaQAAAACcAAABPA==</packet>
  </message>
  <message info="Receiver: 3838. From: 192.168.1.23:48547" type="Received">
    <packet>L2RlZXBsYWIvYm93bAAAACxpaQAAAACcAAABPQ==</packet>
  </message>
  <message info="Receiver: 3838. From: 192.168.1.23:48547" type="Received">
    <packet>L2RlZXBsYWIvYm93bAAAACxpaQAAAACcAAABPQ==</packet>
  </message>
  <message info="Receiver: 3838. From: 192.168.1.23:48547" type="Received">
    <packet>L2RlZXBsYWIvYm93bAAAACxpaQAAAACcAAABPQ==</packet>
  </message>
  <message info="Receiver: 3838. From: 192.168.1.23:48547" type="Received">
    <packet>L2RlZXBsYWIvYm93bAAAACxpaQAAAACcAAABPQ==</packet>
  </message>
  <message info="Receiver: 3838. From: 192.168.1.23:48547" type="Received">
    <packet>L2RlZXBsYWIvYm93bAAAACxpaQAAAACcAAABPA==</packet>
  </message>
  <message info="Receiver: 3838. From: 192.168.1.23:48547" type="Received">
    <packet>L2RlZXBsYWIvYm93bAAAACxpaQAAAACdAAABPA==</packet>
  </message>
  <message info="Receiver: 3838. From: 192.168.1.23:48547" type="Received">
    <packet>L2RlZXBsYWIvYm93bAAAACxpaQAAAACdAAAA6A==</packet>
  </message>
  <message info="Receiver: 3838. From: 192.168.1.23:48547" type="Received">
    <packet>L2RlZXBsYWIvYm93bAAAACxpaQAAAACfAAAA6Q==</packet>
  </message>
  <message info="Receiver: 3838. From: 192.168.1.23:48547" type="Received">
    <packet>L2RlZXBsYWIvYm93bAAAACxpaQAAAACfAAABPA==</packet>
  </message>
  <message info="Receiver: 3838. From: 192.168.1.23:48547" type="Received">
    <packet>L2RlZXBsYWIvYm93bAAAACxpaQAAAACfAAAA6Q==</packet>
  </message>
  <message info="Receiver: 3838. From: 192.168.1.23:48547" type="Received">
    <packet>L2RlZXBsYWIvYm93bAAAACxpaQAAAACeAAABOw==</packet>
  </message>
  <message info="Receiver: 3838. From: 192.168.1.23:48547" type="Received">
    <packet>L2RlZXBsYWIvYm93bAAAACxpaQAAAACfAAABMQ==</packet>
  </message>
  <message info="Receiver: 3838. From: 192.168.1.23:48547" type="Received">
    <packet>L2RlZXBsYWIvYm93bAAAACxpaQAAAACeAAAA6Q==</packet>
  </message>
  <message info="Receiver: 3838. From: 192.168.1.23:48547" type="Received">
    <packet>L2RlZXBsYWIvYm93bAAAACxpaQAAAACfAAABMA==</packet>
  </message>
  <message info="Receiver: 3838. From: 192.168.1.23:48547" type="Received">
    <packet>L2RlZXBsYWIvYm93bAAAACxpaQAAAACdAAAA6g==</packet>
  </message>
  <message info="Receiver: 3838. From: 192.168.1.23:48547" type="Received">
    <packet>L2RlZXBsYWIvYm93bAAAACxpaQAAAACPAAABGA==</packet>
  </message>
  <message info="Receiver: 3838. From: 192.168.1.23:48547" type="Received">
    <packet>L2RlZXBsYWIvYm93bAAAACxpaQAAAACfAAAA6g==</packet>
  </message>
  <message info="Receiver: 3838. From: 192.168.1.23:48547" type="Received">
    <packet>L2RlZXBsYWIvYm93bAAAACxpaQAAAACfAAAA6A==</packet>
  </message>
  <message info="Receiver: 3838. From: 192.168.1.23:48547" type="Received">
    <packet>L2RlZXBsYWIvYm93bAAAACxpaQAAAACfAAABPA==</packet>
  </message>
  <message info="Receiver: 3838. From: 192.168.1.23:48547" type="Received">
    <packet>L2RlZXBsYWIvYm93bAAAACxpaQAAAACfAAABOw==</packet>
  </message>
  <message info="Receiver: 3838. From: 192.168.1.23:48547" type="Received">
    <packet>L2RlZXBsYWIvYm93bAAAACxpaQAAAACfAAAA6Q==</packet>
  </message>
  <message info="Receiver: 3838. From: 192.168.1.23:48547" type="Received">
    <packet>L2RlZXBsYWIvYm93bAAAACxpaQAAAACfAAAA6Q==</packet>
  </message>
  <message info="Receiver: 3838. From: 192.168.1.23:48547" type="Received">
    <packet>L2RlZXBsYWIvYm93bAAAACxpaQAAAACfAAAA6g==</packet>
  </message>
  <message info="Receiver: 3838. From: 192.168.1.23:48547" type="Received">
    <packet>L2RlZXBsYWIvYm93bAAAACxpaQAAAACfAAAA6Q==</packet>
  </message>
  <message info="Receiver: 3838. From: 192.168.1.23:48547" type="Received">
    <packet>L2RlZXBsYWIvYm93bAAAACxpaQAAAACfAAAA6g==</packet>
  </message>
  <message info="Receiver: 3838. From: 192.168.1.23:48547" type="Received">
    <packet>L2RlZXBsYWIvYm93bAAAACxpaQAAAACeAAAA6A==</packet>
  </message>
  <message info="Receiver: 3838. From: 192.168.1.23:48547" type="Received">
    <packet>L2RlZXBsYWIvYm93bAAAACxpaQAAAACfAAAA5w==</packet>
  </message>
  <message info="Receiver: 3838. From: 192.168.1.23:48547" type="Received">
    <packet>L2RlZXBsYWIvYm93bAAAACxpaQAAAACeAAAA5w==</packet>
  </message>
  <message info="Receiver: 3838. From: 192.168.1.23:48547" type="Received">
    <packet>L2RlZXBsYWIvYm93bAAAACxpaQAAAACeAAAA5w==</packet>
  </message>
  <message info="Receiver: 3838. From: 192.168.1.23:48547" type="Received">
    <packet>L2RlZXBsYWIvYm93bAAAACxpaQAAAACeAAAA5w==</packet>
  </message>
  <message info="Receiver: 3838. From: 192.168.1.23:48547" type="Received">
    <packet>L2RlZXBsYWIvYm93bAAAACxpaQAAAACeAAAA5w==</packet>
  </message>
  <message info="Receiver: 3838. From: 192.168.1.23:48547" type="Received">
    <packet>L2RlZXBsYWIvYm93bAAAACxpaQAAAACfAAAA6Q==</packet>
  </message>
  <message info="Receiver: 3838. From: 192.168.1.23:48547" type="Received">
    <packet>L2RlZXBsYWIvYm93bAAAACxpaQAAAACfAAAA6Q==</packet>
  </message>
  <message info="Receiver: 3838. From: 192.168.1.23:48547" type="Received">
    <packet>L2RlZXBsYWIvYm93bAAAACxpaQAAAACfAAAA6Q==</packet>
  </message>
  <message info="Receiver: 3838. From: 192.168.1.23:48547" type="Received">
    <packet>L2RlZXBsYWIvYm93bAAAACxpaQAAAACfAAAA6Q==</packet>
  </message>
  <message info="Receiver: 3838. From: 192.168.1.23:48547" type="Received">
    <packet>L2RlZXBsYWIvYm93bAAAACxpaQAAAACeAAABPA==</packet>
  </message>
  <message info="Receiver: 3838. From: 192.168.1.23:48547" type="Received">
    <packet>L2RlZXBsYWIvYm93bAAAACxpaQAAAACeAAABOw==</packet>
  </message>
  <message info="Receiver: 3838. From: 192.168.1.23:48547" type="Received">
    <packet>L2RlZXBsYWIvYm93bAAAACxpaQAAAACeAAABOw==</packet>
  </message>
  <message info="Receiver: 3838. From: 192.168.1.23:48547" type="Received">
    <packet>L2RlZXBsYWIvYm93bAAAACxpaQAAAAC6AAAA6Q==</packet>
  </message>
  <message info="Receiver: 3838. From: 192.168.1.23:48547" type="Received">
    <packet>L2RlZXBsYWIvYm93bAAAACxpaQAAAAC7AAAA6Q==</packet>
  </message>
  <message info="Receiver: 3838. From: 192.168.1.23:48547" type="Received">
    <packet>L2RlZXBsYWIvYm93bAAAACxpaQAAAAC/AAAA6Q==</packet>
  </message>
  <message info="Receiver: 3838. From: 192.168.1.23:48547" type="Received">
    <packet>L2RlZXBsYWIvYm93bAAAACxpaQAAAAC8AAAA6Q==</packet>
  </message>
  <message info="Receiver: 3838. From: 192.168.1.23:48547" type="Received">
    <packet>L2RlZXBsYWIvYm93bAAAACxpaQAAAAC7AAAA6Q==</packet>
  </message>
  <message info="Receiver: 3838. From: 192.168.1.23:48547" type="Received">
    <packet>L2RlZXBsYWIvYm93bAAAACxpaQAAAAC7AAAA6A==</packet>
  </message>
  <message info="Receiver: 3838. From: 192.168.1.23:48547" type="Received">
    <packet>L2RlZXBsYWIvYm93bAAAACxpaQAAAAC7AAAA5w==</packet>
  </message>
  <message info="Receiver: 3838. From: 192.168.1.23:48547" type="Received">
    <packet>L2RlZXBsYWIvYm93bAAAACxpaQAAAAC7AAAA6A==</packet>
  </message>
  <message info="Receiver: 3838. From: 192.168.1.23:48547" type="Received">
    <packet>L2RlZXBsYWIvYm93bAAAACxpaQAAAAC9AAAA6A==</packet>
  </message>
  <message info="Receiver: 3838. From: 192.168.1.23:48547" type="Received">
    <packet>L2RlZXBsYWIvYm93bAAAACxpaQAAAACmAAAAgQ==</packet>
  </message>
  <message info="Receiver: 3838. From: 192.168.1.23:48547" type="Received">
    <packet>L2RlZXBsYWIvYm93bAAAACxpaQAAAACkAAAA4Q==</packet>
  </message>
  <message info="Receiver: 3838. From: 192.168.1.23:48547" type="Received">
    <packet>L2RlZXBsYWIvYm93bAAAACxpaQAAAACkAAAAhg==</packet>
  </message>
  <message info="Receiver: 3838. From: 192.168.1.23:48547" type="Received">
    <packet>L2RlZXBsYWIvYm93bAAAACxpaQAAAACjAAAAhQ==</packet>
  </message>
  <message info="Receiver: 3838. From: 192.168.1.23:48547" type="Received">
    <packet>L2RlZXBsYWIvYm93bAAAACxpaQAAAACkAAAAhg==</packet>
  </message>
  <message info="Receiver: 3838. From: 192.168.1.23:48547" type="Received">
    <packet>L2RlZXBsYWIvYm93bAAAACxpaQAAAACjAAAAhw==</packet>
  </message>
  <message info="Receiver: 3838. From: 192.168.1.23:48547" type="Received">
    <packet>L2RlZXBsYWIvYm93bAAAACxpaQAAAAC2AAAA5g==</packet>
  </message>
  <message info="Receiver: 3838. From: 192.168.1.23:48547" type="Received">
    <packet>L2RlZXBsYWIvYm93bAAAACxpaQAAAAC1AAAA5Q==</packet>
  </message>
  <message info="Receiver: 3838. From: 192.168.1.23:48547" type="Received">
    <packet>L2RlZXBsYWIvYm93bAAAACxpaQAAAAC2AAAA5Q==</packet>
  </message>
  <message info="Receiver: 3838. From: 192.168.1.23:48547" type="Received">
    <packet>L2RlZXBsYWIvYm93bAAAACxpaQAAAAC0AAAA1A==</packet>
  </message>
  <message info="Receiver: 3838. From: 192.168.1.23:48547" type="Received">
    <packet>L2RlZXBsYWIvYm93bAAAACxpaQAAAAC1AAAA5g==</packet>
  </message>
  <message info="Receiver: 3838. From: 192.168.1.23:48547" type="Received">
    <packet>L2RlZXBsYWIvYm93bAAAACxpaQAAAAC2AAAA6Q==</packet>
  </message>
  <message info="Receiver: 3838. From: 192.168.1.23:48547" type="Received">
    <packet>L2RlZXBsYWIvYm93bAAAACxpaQAAAACzAAAAxA==</packet>
  </message>
  <message info="Receiver: 3838. From: 192.168.1.23:48547" type="Received">
    <packet>L2RlZXBsYWIvYm93bAAAACxpaQAAAAC2AAAAxg==</packet>
  </message>
  <message info="Receiver: 3838. From: 192.168.1.23:48547" type="Received">
    <packet>L2RlZXBsYWIvYm93bAAAACxpaQAAAAC4AAAA6g==</packet>
  </message>
  <message info="Receiver: 3838. From: 192.168.1.23:48547" type="Received">
    <packet>L2RlZXBsYWIvYm93bAAAACxpaQAAAAC1AAAAzw==</packet>
  </message>
  <message info="Receiver: 3838. From: 192.168.1.23:48547" type="Received">
    <packet>L2RlZXBsYWIvYm93bAAAACxpaQAAAAC2AAAAyQ==</packet>
  </message>
  <message info="Receiver: 3838. From: 192.168.1.23:48547" type="Received">
    <packet>L2RlZXBsYWIvYm93bAAAACxpaQAAAAC3AAAA1g==</packet>
  </message>
  <message info="Receiver: 3838. From: 192.168.1.23:48547" type="Received">
    <packet>L2RlZXBsYWIvYm93bAAAACxpaQAAAAC4AAAA1w==</packet>
  </message>
  <message info="Receiver: 3838. From: 192.168.1.23:48547" type="Received">
    <packet>L2RlZXBsYWIvYm93bAAAACxpaQAAAAC2AAAA0w==</packet>
  </message>
  <message info="Receiver: 3838. From: 192.168.1.23:48547" type="Received">
    <packet>L2RlZXBsYWIvYm93bAAAACxpaQAAAAC2AAAA0Q==</packet>
  </message>
  <message info="Receiver: 3838. From: 192.168.1.23:48547" type="Received">
    <packet>L2RlZXBsYWIvYm93bAAAACxpaQAAAAC2AAAA0w==</packet>
  </message>
  <message info="Receiver: 3838. From: 192.168.1.23:48547" type="Received">
    <packet>L2RlZXBsYWIvYm93bAAAACxpaQAAAACeAAAAtA==</packet>
  </message>
  <message info="Receiver: 3838. From: 192.168.1.23:48547" type="Received">
    <packet>L2RlZXBsYWIvYm93bAAAACxpaQAAAACeAAAAsw==</packet>
  </message>
  <message info="Receiver: 3838. From: 192.168.1.23:48547" type="Received">
    <packet>L2RlZXBsYWIvYm93bAAAACxpaQAAAACeAAAAsg==</packet>
  </message>
  <message info="Receiver: 3838. From: 192.168.1.23:48547" type="Received">
    <packet>L2RlZXBsYWIvYm93bAAAACxpaQAAAACeAAAAsw==</packet>
  </message>
  <message info="Receiver: 3838. From: 192.168.1.23:48547" type="Received">
    <packet>L2RlZXBsYWIvYm93bAAAACxpaQAAAACdAAAAsw==</packet>
  </message>
  <message info="Receiver: 3838. From: 192.168.1.23:48547" type="Received">
    <packet>L2RlZXBsYWIvYm93bAAAACxpaQAAAACeAAAAsg==</packet>
  </message>
  <message info="Receiver: 3838. From: 192.168.1.23:48547" type="Received">
    <packet>L2RlZXBsYWIvYm93bAAAACxpaQAAAACdAAAAsw==</packet>
  </message>
  <message info="Receiver: 3838. From: 192.168.1.23:48547" type="Received">
    <packet>L2RlZXBsYWIvYm93bAAAACxpaQAAAACeAAAArg==</packet>
  </message>
  <message info="Receiver: 3838. From: 192.168.1.23:48547" type="Received">
    <packet>L2RlZXBsYWIvYm93bAAAACxpaQAAAACjAAAAhw==</packet>
  </message>
  <message info="Receiver: 3838. From: 192.168.1.23:48547" type="Received">
    <packet>L2RlZXBsYWIvYm93bAAAACxpaQAAAACjAAAAiA==</packet>
  </message>
  <message info="Receiver: 3838. From: 192.168.1.23:48547" type="Received">
    <packet>L2RlZXBsYWIvYm93bAAAACxpaQAAAACiAAAAiA==</packet>
  </message>
  <message info="Receiver: 3838. From: 192.168.1.23:48547" type="Received">
    <packet>L2RlZXBsYWIvYm93bAAAACxpaQAAAACjAAAAhw==</packet>
  </message>
  <message info="Receiver: 3838. From: 192.168.1.23:48547" type="Received">
    <packet>L2RlZXBsYWIvYm93bAAAACxpaQAAAACeAAAAzQ==</packet>
  </message>
  <message info="Receiver: 3838. From: 192.168.1.23:48547" type="Received">
    <packet>L2RlZXBsYWIvYm93bAAAACxpaQAAAACWAAAAng==</packet>
  </message>
  <message info="Receiver: 3838. From: 192.168.1.23:48547" type="Received">
    <packet>L2RlZXBsYWIvYm93bAAAACxpaQAAAACiAAAAgg==</packet>
  </message>
  <message info="Receiver: 3838. From: 192.168.1.23:48547" type="Received">
    <packet>L2RlZXBsYWIvYm93bAAAACxpaQAAAACiAAAAhQ==</packet>
  </message>
</root>